lightning_lite/CHANGELOG.md
lightning_lite/README.md
lightning_lite/__about__.py
lightning_lite/__init__.py
lightning_lite/__setup__.py
lightning_lite/__version__.py
lightning_lite/connector.py
lightning_lite/lite.py
lightning_lite/wrappers.py
lightning_lite/accelerators/__init__.py
lightning_lite/accelerators/accelerator.py
lightning_lite/accelerators/cpu.py
lightning_lite/accelerators/cuda.py
lightning_lite/accelerators/mps.py
lightning_lite/accelerators/registry.py
lightning_lite/accelerators/tpu.py
lightning_lite/plugins/__init__.py
lightning_lite/plugins/collectives/__init__.py
lightning_lite/plugins/collectives/collective.py
lightning_lite/plugins/collectives/single_device.py
lightning_lite/plugins/collectives/torch_collective.py
lightning_lite/plugins/environments/__init__.py
lightning_lite/plugins/environments/cluster_environment.py
lightning_lite/plugins/environments/kubeflow.py
lightning_lite/plugins/environments/lightning.py
lightning_lite/plugins/environments/lsf.py
lightning_lite/plugins/environments/slurm.py
lightning_lite/plugins/environments/torchelastic.py
lightning_lite/plugins/environments/xla.py
lightning_lite/plugins/io/__init__.py
lightning_lite/plugins/io/checkpoint_io.py
lightning_lite/plugins/io/torch_io.py
lightning_lite/plugins/io/xla.py
lightning_lite/plugins/precision/__init__.py
lightning_lite/plugins/precision/deepspeed.py
lightning_lite/plugins/precision/double.py
lightning_lite/plugins/precision/native_amp.py
lightning_lite/plugins/precision/precision.py
lightning_lite/plugins/precision/tpu.py
lightning_lite/plugins/precision/tpu_bf16.py
lightning_lite/plugins/precision/utils.py
lightning_lite/strategies/__init__.py
lightning_lite/strategies/ddp.py
lightning_lite/strategies/ddp_spawn.py
lightning_lite/strategies/deepspeed.py
lightning_lite/strategies/dp.py
lightning_lite/strategies/fairscale.py
lightning_lite/strategies/parallel.py
lightning_lite/strategies/registry.py
lightning_lite/strategies/single_device.py
lightning_lite-1.8.6.dist-info/LICENSE
lightning_lite-1.8.6.dist-info/METADATA
lightning_lite-1.8.6.dist-info/WHEEL
lightning_lite-1.8.6.dist-info/top_level.txt
lightning_lite-1.8.6.dist-info/RECORD
