Metadata-Version: 2.1
Name: lightning-lite
Version: 1.8.6
Summary: UNKNOWN
Home-page: https://github.com/Lightning-AI/lightning
Author: Lightning AI et al.
Author-email: pytorch@lightning.ai
License: Apache-2.0
Download-URL: https://github.com/Lightning-AI/lightning
Project-URL: Bug Tracker, https://github.com/Lightning-AI/lightning/issues
Project-URL: Documentation, https://pytorch-lightning.rtfd.io/en/latest/
Project-URL: Source Code, https://github.com/Lightning-AI/lightning
Keywords: deep learning,pytorch,AI
Platform: UNKNOWN
Classifier: Environment :: Console
Classifier: Natural Language :: English
Classifier: Development Status :: 4 - Beta
Classifier: Intended Audience :: Developers
Classifier: Topic :: Scientific/Engineering :: Artificial Intelligence
Classifier: Topic :: Scientific/Engineering :: Information Analysis
Classifier: Operating System :: OS Independent
Classifier: Programming Language :: Python :: 3
Classifier: Programming Language :: Python :: 3.7
Classifier: Programming Language :: Python :: 3.8
Classifier: Programming Language :: Python :: 3.9
Classifier: Programming Language :: Python :: 3.10
Requires-Python: >=3.7
License-File: LICENSE
Requires-Dist: numpy (>=1.17.2)
Requires-Dist: torch (>=1.9.0)
Requires-Dist: fsspec[http] (>2021.06.0)
Requires-Dist: packaging (>=17.0)
Requires-Dist: typing-extensions (>=4.0.0)
Requires-Dist: lightning-utilities (!=0.4.0,>=0.3.0)
Provides-Extra: all
Requires-Dist: coverage (==6.5.0) ; extra == 'all'
Requires-Dist: codecov (==2.1.12) ; extra == 'all'
Requires-Dist: pytest (==7.2.0) ; extra == 'all'
Requires-Dist: pytest-cov (==4.0.0) ; extra == 'all'
Requires-Dist: pre-commit (==2.20.0) ; extra == 'all'
Requires-Dist: fairscale (>=0.4.5) ; extra == 'all'
Requires-Dist: deepspeed (>=0.6.0) ; extra == 'all'
Provides-Extra: deepspeed
Requires-Dist: deepspeed (>=0.6.0) ; extra == 'deepspeed'
Provides-Extra: dev
Requires-Dist: coverage (==6.5.0) ; extra == 'dev'
Requires-Dist: codecov (==2.1.12) ; extra == 'dev'
Requires-Dist: pytest (==7.2.0) ; extra == 'dev'
Requires-Dist: pytest-cov (==4.0.0) ; extra == 'dev'
Requires-Dist: pre-commit (==2.20.0) ; extra == 'dev'
Provides-Extra: fairscale
Requires-Dist: fairscale (>=0.4.5) ; extra == 'fairscale'
Provides-Extra: strategies
Requires-Dist: fairscale (>=0.4.5) ; extra == 'strategies'
Requires-Dist: deepspeed (>=0.6.0) ; extra == 'strategies'
Provides-Extra: test
Requires-Dist: coverage (==6.5.0) ; extra == 'test'
Requires-Dist: codecov (==2.1.12) ; extra == 'test'
Requires-Dist: pytest (==7.2.0) ; extra == 'test'
Requires-Dist: pytest-cov (==4.0.0) ; extra == 'test'
Requires-Dist: pre-commit (==2.20.0) ; extra == 'test'
